Metadata-Version: 2.1
Name: scrape-instagram
Version: 1.0.1
Summary: A python library to scrape instagram profile ,comments, follower, etc.
Home-page: UNKNOWN
Author: DataKund
Author-email: datakund@gmail.com
License: Apache License 2.0
Keywords: insta instagram profile like comment python bot_studio automation search scraper scrape follower following profile posts like comment
Platform: UNKNOWN
License-File: LICENSE
